setup.py
th_py_spider_core.egg-info/PKG-INFO
th_py_spider_core.egg-info/SOURCES.txt
th_py_spider_core.egg-info/dependency_links.txt
th_py_spider_core.egg-info/requires.txt
th_py_spider_core.egg-info/top_level.txt
th_spider_core/__init__.py
th_spider_core/admin.py
th_spider_core/geteway.py
th_spider_core/geteway_transation.py
th_spider_core/message_task.py
th_spider_core/time_task.py
th_spider_core/utils/__init__.py
th_spider_core/utils/tx_ms_utils.py