Metadata-Version: 1.0
Name: th_py_spider_core
Version: 1.7
Summary: 听海内部爬虫核心类库
Home-page: UNKNOWN
Author: wzr
Author-email: 510540795@qq.com
License: MIT Licence
Platform: any
